flashsurvey/__init__.py
flashsurvey/lib.py
flashsurvey-0.0.1.dist-info/LICENSE.txt
flashsurvey-0.0.1.dist-info/METADATA
flashsurvey-0.0.1.dist-info/WHEEL
flashsurvey-0.0.1.dist-info/top_level.txt
flashsurvey-0.0.1.dist-info/RECORD
