Metadata-Version: 2.1
Name: flashsurvey
Version: 0.0.1
Summary: work in progress
Author-email: Alexander Schau <alexander@schau.email>
Project-URL: Homepage, https://flaz.it
Classifier: Programming Language :: Python :: 3
Classifier: Operating System :: OS Independent
Requires-Python: >=3.6
License-File: LICENSE.txt
